<?xml version="1.0" encoding="UTF-8"?>

<!--
File appender logback configuration provided for import, equivalent to the programmatic
initialization performed by Boot
-->

<included>
	<appender name="FILE" class="ch.qos.logback.core.rolling.RollingFileAppender">
		<encoder>
			<pattern>${FILE_LOG_PATTERN}</pattern>
		</encoder>
		<file>${LOG_FILE}</file>
		<rollingPolicy class="ch.qos.logback.core.rolling.FixedWindowRollingPolicy">
			<fileNamePattern>${LOG_FILE}.%i</fileNamePattern>
			<minIndex>0</minIndex>
			<maxIndex>19</maxIndex>
		</rollingPolicy>
		<triggeringPolicy class="ch.qos.logback.core.rolling.SizeBasedTriggeringPolicy">
			<maxFileSize>10MB</maxFileSize>
		</triggeringPolicy>
	</appender>
</included>
